{
    "vol": "y",
    "cont": "y",
    "quality": "clean_audio",
    "stage": "breathing-deep",
    "start_1": 1.987,
    "end_1": 3.285,
    "start_2": 3.829,
    "end_2": 5.215,
    "start_3": 5.777,
    "end_3": 7.198,
    "start_4": 8.198,
    "end_4": 9.865,
    "start_5": 10.479,
    "end_5": 11.637,
    "start_6": 12.409,
    "end_6": 13.901,
    "start_7": 14.181,
    "end_7": 15.48,
    "start_8": 16.497,
    "end_8": 17.884,
    "start_9": 18.375,
    "end_9": 19.428,
    "start_10": 20.393,
    "end_10": 22.077,
    "annotator_name": "Rohit Kumar"
}